{
  "top": [
    {
      "ruota": "Palermo",
      "ultima_estrazione": [
        37,
        55,
        68,
        33,
        11
      ],
      "terno": [
        26,
        84,
        78
      ],
      "score": 4564
    },
    {
      "ruota": "Roma",
      "ultima_estrazione": [
        1,
        4,
        36,
        81,
        38
      ],
      "terno": [
        67,
        66,
        14
      ],
      "score": 4541
    },
    {
      "ruota": "Bari",
      "ultima_estrazione": [
        38,
        78,
        24,
        40,
        33
      ],
      "terno": [
        24,
        52,
        81
      ],
      "score": 4371
    }
  ],
  "jolly": {
    "ruota": "Palermo",
    "ultima_estrazione": [
      37,
      55,
      68,
      33,
      11
    ],
    "terno": [
      26,
      84,
      78
    ],
    "score": 4564
  },
  "terno_forte": [
    {
      "ruota": "Palermo",
      "ultima_estrazione": [
        37,
        55,
        68,
        33,
        11
      ],
      "terno": [
        26,
        84,
        78
      ],
      "score": 4564
    },
    {
      "ruota": "Roma",
      "ultima_estrazione": [
        1,
        4,
        36,
        81,
        38
      ],
      "terno": [
        67,
        66,
        14
      ],
      "score": 4541
    },
    {
      "ruota": "Bari",
      "ultima_estrazione": [
        38,
        78,
        24,
        40,
        33
      ],
      "terno": [
        24,
        52,
        81
      ],
      "score": 4371
    },
    {
      "ruota": "Venezia",
      "ultima_estrazione": [
        70,
        85,
        24,
        56,
        53
      ],
      "terno": [
        36,
        89,
        67
      ],
      "score": 4276
    },
    {
      "ruota": "Cagliari",
      "ultima_estrazione": [
        26,
        80,
        5,
        1,
        48
      ],
      "terno": [
        49,
        31,
        59
      ],
      "score": 4217
    },
    {
      "ruota": "Torino",
      "ultima_estrazione": [
        17,
        15,
        75,
        69,
        76
      ],
      "terno": [
        75,
        59,
        26
      ],
      "score": 4180
    },
    {
      "ruota": "Genova",
      "ultima_estrazione": [
        68,
        39,
        49,
        59,
        13
      ],
      "terno": [
        43,
        19,
        9
      ],
      "score": 4113
    },
    {
      "ruota": "Firenze",
      "ultima_estrazione": [
        80,
        71,
        74,
        22,
        67
      ],
      "terno": [
        15,
        72,
        50
      ],
      "score": 4111
    },
    {
      "ruota": "Napoli",
      "ultima_estrazione": [
        43,
        80,
        6,
        78,
        82
      ],
      "terno": [
        16,
        7,
        76
      ],
      "score": 3897
    },
    {
      "ruota": "Milano",
      "ultima_estrazione": [
        40,
        19,
        8,
        62,
        84
      ],
      "terno": [
        21,
        8,
        68
      ],
      "score": 3791
    }
  ]
}